grai_actions/__init__.py
grai_actions/config.py
grai_actions/git_messages.py
grai_actions/integrations/__init__.py
grai_actions/integrations/bigquery/__init__.py
grai_actions/integrations/dbt/__init__.py
grai_actions/integrations/fivetran/__init__.py
grai_actions/integrations/flat_file/__init__.py
grai_actions/integrations/mssql/__init__.py
grai_actions/integrations/mysql/__init__.py
grai_actions/integrations/postgres/__init__.py
grai_actions/integrations/redshift/__init__.py
grai_actions/integrations/snowflake/__init__.py
grai_actions/main.py
grai_actions/tools.py
grai_actions/utilities.py
grai_actions-0.2.4.dist-info/LICENSE
grai_actions-0.2.4.dist-info/METADATA
grai_actions-0.2.4.dist-info/WHEEL
grai_actions-0.2.4.dist-info/entry_points.txt
grai_actions-0.2.4.dist-info/RECORD
